pyspark_dist_explore/__init__.py
pyspark_dist_explore/pyspark_dist_explore.py
pyspark_dist_explore-0.1.7.dist-info/METADATA
pyspark_dist_explore-0.1.7.dist-info/RECORD
pyspark_dist_explore-0.1.7.dist-info/WHEEL
pyspark_dist_explore-0.1.7.dist-info/top_level.txt
